fanumbers/__init__.py
fanumbers/consts.py
fanumbers/numbers.py
fanumbers/utils.py
fanumbers/words.py
fanumbers-1.0.1.dist-info/METADATA
fanumbers-1.0.1.dist-info/RECORD
fanumbers-1.0.1.dist-info/WHEEL
fanumbers-1.0.1.dist-info/top_level.txt
