Metadata-Version: 2.1
Name: fanumbers
Version: 1.0.1
Summary: Library to work with Farsi (Persian) numbers
Home-page: https://github.com/amirmd76/fanumbers
Author: AmirMohammad Dehghan
Author-email: amirmd76@gmail.com
License: UNKNOWN
Platform: UNKNOWN
